GustavSelfBot/__bot__.py
GustavSelfBot/__config__.py
GustavSelfBot/__init__.py
GustavSelfBot/__logging__.py
GustavSelfBot/Commands/__commands__.py
GustavSelfBot/Commands/__init__.py
GustavSelfBot/Commands/Functions/__init__.py
GustavSelfBot/Commands/Functions/__logs__.py
GustavSelfBot/Commands/Functions/__ping__.py
GustavSelfBot/Commands/Functions/__quote__.py
GustavSelfBot/Commands/Functions/__search__.py
GustavSelfBot/Commands/Functions/helpers/__embed__.py
GustavSelfBot/Commands/Functions/helpers/__init__.py
GustavSelfBot/Events/__init__.py
GustavSelfBot/Events/__on_message__.py
GustavSelfBot/Events/__on_ready__.py
GustavSelfBot/Events/__on_voice_state_update__.py
gustavselfbot-0.0.8.dist-info/LICENSE
gustavselfbot-0.0.8.dist-info/WHEEL
gustavselfbot-0.0.8.dist-info/METADATA
gustavselfbot-0.0.8.dist-info/RECORD
